st_keyup/__init__.py
st_keyup/frontend/index.html
st_keyup/frontend/main.js
st_keyup/frontend/streamlit-component-lib.js
st_keyup/frontend/style.css
streamlit_keyup-0.2.4.dist-info/LICENSE
streamlit_keyup-0.2.4.dist-info/METADATA
streamlit_keyup-0.2.4.dist-info/WHEEL
streamlit_keyup-0.2.4.dist-info/top_level.txt
streamlit_keyup-0.2.4.dist-info/RECORD
